asksage_proxy/__init__.py
asksage_proxy/app.py
asksage_proxy/cli.py
asksage_proxy/client.py
asksage_proxy/config.py
asksage_proxy/models.py
asksage_proxy/endpoints/__init__.py
asksage_proxy/endpoints/chat.py
asksage_proxy/endpoints/extras.py
asksage_proxy/endpoints/models.py
asksage_proxy/types/__init__.py
asksage_proxy/types/chat_completion.py
asksage_proxy/types/completions.py
asksage_proxy/types/function_call.py
asksage_proxy/utils/__init__.py
asksage_proxy/utils/config_helpers.py
asksage_proxy/utils/misc.py
asksage_proxy-0.3.0.dist-info/METADATA
asksage_proxy-0.3.0.dist-info/WHEEL
asksage_proxy-0.3.0.dist-info/entry_points.txt
asksage_proxy-0.3.0.dist-info/top_level.txt
asksage_proxy-0.3.0.dist-info/RECORD
